exifread-stubs/METADATA.toml
exifread-stubs/__init__.pyi
exifread-stubs/_types.pyi
exifread-stubs/classes.pyi
exifread-stubs/exceptions.pyi
exifread-stubs/exif_log.pyi
exifread-stubs/heic.pyi
exifread-stubs/jpeg.pyi
exifread-stubs/py.typed
exifread-stubs/utils.pyi
types_exifread-3.0.0.20250401.dist-info/licenses/LICENSE
types_exifread-3.0.0.20250401.dist-info/METADATA
types_exifread-3.0.0.20250401.dist-info/WHEEL
types_exifread-3.0.0.20250401.dist-info/top_level.txt
types_exifread-3.0.0.20250401.dist-info/RECORD
